MANIFEST.in
setup.py
Products/__init__.py
Products.SilvaDocument.egg-info/PKG-INFO
Products.SilvaDocument.egg-info/SOURCES.txt
Products.SilvaDocument.egg-info/dependency_links.txt
Products.SilvaDocument.egg-info/namespace_packages.txt
Products.SilvaDocument.egg-info/not-zip-safe
Products.SilvaDocument.egg-info/requires.txt
Products.SilvaDocument.egg-info/top_level.txt
Products/SilvaDocument/Document.py
Products/SilvaDocument/HISTORY.txt
Products/SilvaDocument/INSTALL.txt
Products/SilvaDocument/LICENSE.txt
Products/SilvaDocument/README.txt
Products/SilvaDocument/__init__.py
Products/SilvaDocument/configure.zcml
Products/SilvaDocument/document.xslt
Products/SilvaDocument/externalsource.py
Products/SilvaDocument/ftesting.zcml
Products/SilvaDocument/ftesting30.zcml
Products/SilvaDocument/install.py
Products/SilvaDocument/interfaces.py
Products/SilvaDocument/path.py
Products/SilvaDocument/testing.py
Products/SilvaDocument/i18n/__init__.py
Products/SilvaDocument/i18n/silva_document.pot
Products/SilvaDocument/i18n/da/LC_MESSAGES/silva_document.mo
Products/SilvaDocument/i18n/da/LC_MESSAGES/silva_document.po
Products/SilvaDocument/i18n/de/LC_MESSAGES/silva_document.mo
Products/SilvaDocument/i18n/de/LC_MESSAGES/silva_document.po
Products/SilvaDocument/i18n/el/LC_MESSAGES/silva_document.mo
Products/SilvaDocument/i18n/el/LC_MESSAGES/silva_document.po
Products/SilvaDocument/i18n/en/LC_MESSAGES/silva_document.mo
Products/SilvaDocument/i18n/en/LC_MESSAGES/silva_document.po
Products/SilvaDocument/i18n/en_GB/LC_MESSAGES/silva_document.mo
Products/SilvaDocument/i18n/en_GB/LC_MESSAGES/silva_document.po
Products/SilvaDocument/i18n/es/LC_MESSAGES/silva_document.mo
Products/SilvaDocument/i18n/es/LC_MESSAGES/silva_document.po
Products/SilvaDocument/i18n/fi/LC_MESSAGES/silva_document.mo
Products/SilvaDocument/i18n/fi/LC_MESSAGES/silva_document.po
Products/SilvaDocument/i18n/fr/LC_MESSAGES/silva_document.mo
Products/SilvaDocument/i18n/fr/LC_MESSAGES/silva_document.po
Products/SilvaDocument/i18n/id/LC_MESSAGES/silva_document.mo
Products/SilvaDocument/i18n/id/LC_MESSAGES/silva_document.po
Products/SilvaDocument/i18n/it/LC_MESSAGES/silva_document.mo
Products/SilvaDocument/i18n/it/LC_MESSAGES/silva_document.po
Products/SilvaDocument/i18n/nl/LC_MESSAGES/silva_document.mo
