Metadata-Version: 1.1
Name: Products.SilvaDocument
Version: 3.0.2
Summary: Document content for Silva 2.x.
Home-page: https://github.com/silvacms/Products.SilvaDocument
Author: Infrae
Author-email: info@infrae.com
License: BSD
Keywords: silva cms document zope
Platform: UNKNOWN
Classifier: Framework :: Zope2
Classifier: License :: OSI Approved :: BSD License
Classifier: Programming Language :: Python
Classifier: Topic :: Software Development :: Libraries :: Python Modules
